PyocdLibrary/__init__.py
PyocdLibrary/__version__.py
robotframework_pyocd-0.2.0.dist-info/LICENSE
robotframework_pyocd-0.2.0.dist-info/METADATA
robotframework_pyocd-0.2.0.dist-info/WHEEL
robotframework_pyocd-0.2.0.dist-info/top_level.txt
robotframework_pyocd-0.2.0.dist-info/RECORD
